{
  "ticker": "DE",
  "timeframe": "1m",
  "source": "alpaca",
  "timestamp": "2026-02-26T21:40:27.050582",
  "bars_saved": 895197,
  "date_range": {
    "start": "2016-01-04",
    "end": "2026-02-11",
    "span_years": 10.11
  },
  "quality_check": {
    "passed": true,
    "quality_score": 0.999891420547656,
    "quarantine": false,
    "quarantine_reason": "",
    "rejected_bars": 0,
    "flagged_bars": 243,
    "issues": [
      "stale_price: Flagged 243 bars in 3+ consecutive stale bar sequences",
      "missing_bar_ratio: Expected 1028820 bars, got 895197 (13.0% missing, threshold: 5%)"
    ]
  },
  "ibkr_validation": {
    "valid": true,
    "checked_bars": 0,
    "price_mismatches": 0,
    "bars_replaced": 0,
    "bars_inserted": 0,
    "mismatch_rate": 0.0,
    "missing_in_primary": 0,
    "split_mismatches": 0,
    "error": null
  }
}