{
  "ticker": "MCD",
  "timeframe": "1m",
  "source": "alpaca",
  "timestamp": "2026-02-27T07:07:54.745889+00:00",
  "total_bars_input": 918925,
  "date_range": "2016-01-04 to 2026-02-11",
  "checks": [
    {
      "check_name": "ohlc_consistency",
      "passed": true,
      "rejected_count": 0,
      "flagged_count": 0,
      "message": "Rejected 0 bars with invalid OHLC relationships",
      "details": {}
    },
    {
      "check_name": "non_negative_volume",
      "passed": true,
      "rejected_count": 0,
      "flagged_count": 0,
      "message": "Rejected 0 bars with negative volume",
      "details": {}
    },
    {
      "check_name": "non_negative_prices",
      "passed": true,
      "rejected_count": 0,
      "flagged_count": 0,
      "message": "Rejected 0 bars with zero or negative prices",
      "details": {}
    },
    {
      "check_name": "timestamp_in_rth",
      "passed": true,
      "rejected_count": 0,
      "flagged_count": 0,
      "message": "Rejected 0 bars outside RTH or non-trading days",
      "details": {}
    },
    {
      "check_name": "extreme_bar_return",
      "passed": true,
      "rejected_count": 0,
      "flagged_count": 0,
      "message": "Flagged 0 bars with return > 15.0% (timeframe: 1m)",
      "details": {
        "threshold": 0.15,
        "timeframe": "1m"
      }
    },
    {
      "check_name": "stale_price",
      "passed": false,
      "rejected_count": 0,
      "flagged_count": 69,
      "message": "Flagged 69 bars in 3+ consecutive stale bar sequences",
      "details": {}
    },
    {
      "check_name": "zero_volume_liquid",
      "passed": true,
      "rejected_count": 0,
      "flagged_count": 0,
      "message": "No zero-volume bars (median daily volume: 2424507)",
      "details": {
        "median_daily_volume": 2424507.0
      }
    },
    {
      "check_name": "missing_bar_ratio",
      "passed": false,
      "rejected_count": 0,
      "flagged_count": 0,
      "message": "Expected 1028820 bars, got 918925 (10.7% missing, threshold: 5%)",
      "details": {
        "expected": 1028820,
        "actual": 918925,
        "missing": 109895,
        "missing_ratio": 0.10681654711222566,
        "trading_days": 2638,
        "timeframe": "1m"
      }
    },
    {
      "check_name": "duplicate_timestamps",
      "passed": true,
      "rejected_count": 0,
      "flagged_count": 0,
      "message": "Found 0 duplicate timestamps",
      "details": {
        "duplicate_count": 0
      }
    },
    {
      "check_name": "monotonic_index",
      "passed": true,
      "rejected_count": 0,
      "flagged_count": 0,
      "message": "Timestamps are strictly increasing",
      "details": {}
    },
    {
      "check_name": "overnight_gap",
      "passed": true,
      "rejected_count": 0,
      "flagged_count": 0,
      "message": "Found 2 overnight gaps > 10% (expected for splits/news/weekends)",
      "details": {
        "gaps": [
          {
            "prev_date": "2020-03-13",
            "prev_close": 155.1,
            "date": "2020-03-16",
            "first_open": 137.33,
            "gap_pct": 0.11457124435847832
          },
          {
            "prev_date": "2023-01-23",
            "prev_close": 251.24,
            "date": "2023-01-24",
            "first_open": 220.9,
            "gap_pct": 0.12076102531444044
          }
        ]
      }
    },
    {
      "check_name": "volume_distribution",
      "passed": true,
      "rejected_count": 0,
      "flagged_count": 0,
      "message": "Median daily volume 2424507 shares (OK)",
      "details": {
        "median_daily_volume": 2424507.0
      }
    },
    {
      "check_name": "split_detection",
      "passed": true,
      "rejected_count": 0,
      "flagged_count": 0,
      "message": "Detected 0 potential unadjusted splits (review for data adjustment)",
      "details": {
        "potential_splits": []
      }
    }
  ],
  "total_rejected": 0,
  "total_flagged": 69,
  "total_bars_output": 918925,
  "quality_score": 0.999969964904644,
  "quarantine": false,
  "quarantine_reason": ""
}